deepleapio/__init__.py
deepleapio-0.1.0.dist-info/LICENSE
deepleapio-0.1.0.dist-info/METADATA
deepleapio-0.1.0.dist-info/WHEEL
deepleapio-0.1.0.dist-info/top_level.txt
deepleapio-0.1.0.dist-info/RECORD
